mycalc/calculator.py
leejimin-0.0.2.dist-info/METADATA
leejimin-0.0.2.dist-info/WHEEL
leejimin-0.0.2.dist-info/top_level.txt
leejimin-0.0.2.dist-info/RECORD
