Metadata-Version: 2.1
Name: leejimin
Version: 0.0.2
Summary: nice calculator
Home-page: https://github.com/chunsejin/calc0001
Download-URL: https://github.com/chunsejin/calc0001
Author: sjchun
License: UNKNOWN
Platform: UNKNOWN
Classifier: Programming Language :: Python :: 3
